bai2_to_json/__init__.py
bai2_to_json/bai_json.py
bai2_to_json-0.0.5.dist-info/METADATA
bai2_to_json-0.0.5.dist-info/WHEEL
bai2_to_json-0.0.5.dist-info/licenses/LICENSE
bai2_to_json-0.0.5.dist-info/RECORD
